latex_generator.py
latexgenerator5233_yoloer-5.2.3.3.dist-info/METADATA
latexgenerator5233_yoloer-5.2.3.3.dist-info/WHEEL
latexgenerator5233_yoloer-5.2.3.3.dist-info/top_level.txt
latexgenerator5233_yoloer-5.2.3.3.dist-info/RECORD
