Metadata-Version: 2.1
Name: latexgenerator5233-yoloer
Version: 5.2.3.3
Summary: A simple LaTeX table and image generator
Home-page: https://github.com/gdnjr5233/Advanced-Python_2024
Author: Wangquanyu
Author-email: w1450111904@qq.com
License: UNKNOWN
Keywords: LaTeX,table,image,generator
Platform: UNKNOWN
Requires-Python: >=3.8
